README.md
setup.py
gsuite/__init__.py
gsuite/auth.py
gsuite/google_groups.py
gsuite/google_sheets.py
gsuite.egg-info/PKG-INFO
gsuite.egg-info/SOURCES.txt
gsuite.egg-info/dependency_links.txt
gsuite.egg-info/requires.txt
gsuite.egg-info/top_level.txt