Metadata-Version: 2.1
Name: gsuite
Version: 1.0.0
Summary: Python library to interact with Google Suite API
Home-page: https://github.com/traveloka/gsuite-python-library
Author: Rafi Kurnia Putra
Author-email: rafi.putra@traveloka.com
License: Apache License 2.0
Platform: UNKNOWN
Requires-Python: >=3
